heroX20213005/__init__.py
heroX20213005/sumoftwo.py
PackegePythonLib-1.0.dist-info/LICENSE.txt
PackegePythonLib-1.0.dist-info/METADATA
PackegePythonLib-1.0.dist-info/WHEEL
PackegePythonLib-1.0.dist-info/top_level.txt
PackegePythonLib-1.0.dist-info/RECORD
