Metadata-Version: 2.1
Name: PackegePythonLib
Version: 1.0
Summary: This module is to test how to create a custom python package.
Home-page: UNKNOWN
Author: Dr. Mohammad Abdelrahman
Author-email: dr.m.abdelrahman@gmail.com
License: MIT
Platform: UNKNOWN
License-File: LICENSE.txt
